MP_Functions.py
MP_Functions-0.0.5.dist-info/METADATA
MP_Functions-0.0.5.dist-info/WHEEL
MP_Functions-0.0.5.dist-info/top_level.txt
MP_Functions-0.0.5.dist-info/RECORD
