Metadata-Version: 2.1
Name: MP-Functions
Version: 0.0.5
Summary: Create market profile features
Home-page: UNKNOWN
Author: Pastor Soto
Author-email: sotoblanco263542@gmail.com
License: UNKNOWN
Platform: UNKNOWN
